.gitignore
.gitmodules
CHANGES.txt
COPYRIGHT.txt
LICENSE.txt
README.rst
rtd.txt
setup.cfg
setup.py
docs/.gitignore
docs/Makefile
docs/app.png
docs/conf.py
docs/glossary.rst
docs/index.rst
pyramid_jqm/__init__.py
pyramid_jqm.egg-info/PKG-INFO
pyramid_jqm.egg-info/SOURCES.txt
pyramid_jqm.egg-info/dependency_links.txt
pyramid_jqm.egg-info/entry_points.txt
pyramid_jqm.egg-info/not-zip-safe
pyramid_jqm.egg-info/requires.txt
pyramid_jqm.egg-info/top_level.txt
pyramid_jqm/scaffolds/__init__.py
pyramid_jqm/scaffolds/jqm_starter/CHANGES.txt_tmpl
pyramid_jqm/scaffolds/jqm_starter/MANIFEST.in_tmpl
pyramid_jqm/scaffolds/jqm_starter/README.txt_tmpl
pyramid_jqm/scaffolds/jqm_starter/development.ini_tmpl
pyramid_jqm/scaffolds/jqm_starter/setup.cfg_tmpl
pyramid_jqm/scaffolds/jqm_starter/setup.py_tmpl
pyramid_jqm/scaffolds/jqm_starter/+package+/__init__.py_tmpl
pyramid_jqm/scaffolds/jqm_starter/+package+/views.py_tmpl
pyramid_jqm/scaffolds/jqm_starter/+package+/static/favicon.ico
pyramid_jqm/scaffolds/jqm_starter/+package+/static/index.html
pyramid_jqm/scaffolds/jqm_starter/+package+/static/jquery-1.6.4.min.js
pyramid_jqm/scaffolds/jqm_starter/+package+/static/jquery.mobile-1.0.css
pyramid_jqm/scaffolds/jqm_starter/+package+/static/jquery.mobile-1.0.js
pyramid_jqm/scaffolds/jqm_starter/+package+/static/jquery.mobile-1.0.min.css
pyramid_jqm/scaffolds/jqm_starter/+package+/static/jquery.mobile-1.0.min.js
pyramid_jqm/scaffolds/jqm_starter/+package+/static/jquery.mobile.structure-1.0.css
pyramid_jqm/scaffolds/jqm_starter/+package+/static/jquery.mobile.structure-1.0.min.css
pyramid_jqm/scaffolds/jqm_starter/+package+/static/jquery.toastmessage-0.3-20110510.css
pyramid_jqm/scaffolds/jqm_starter/+package+/static/jquery.toastmessage-0.3-20110510.js
pyramid_jqm/scaffolds/jqm_starter/+package+/static/jquery.validate-1.8.0.js
pyramid_jqm/scaffolds/jqm_starter/+package+/static/mobileinit.js
pyramid_jqm/scaffolds/jqm_starter/+package+/static/modernizr-1.7.js
pyramid_jqm/scaffolds/jqm_starter/+package+/static/modernizr.min.js
pyramid_jqm/scaffolds/jqm_starter/+package+/static/pyramid.css
pyramid_jqm/scaffolds/jqm_starter/+package+/static/pyramid.js
pyramid_jqm/scaffolds/jqm_starter/+package+/static/images/ajax-loader.png
