Metadata-Version: 1.0
Name: pyramid-jqm
Version: 0.2
Summary: a package which provides "starter" scaffolding for creating a jQuery Mobile Pyramid application.
Home-page: http://docs.pylonsproject.org
Author: Chris McDonough
Author-email: pylons-devel@googlegroups.com
License: BSD-derived (http://www.repoze.org/LICENSE.txt)
Keywords: wsgi pylons jqm jquery mobile web pyramid
Platform: UNKNOWN
Classifier: Intended Audience :: Developers
Classifier: Programming Language :: Python
Classifier: Framework :: Pylons
Classifier: Topic :: Internet :: WWW/HTTP :: WSGI
Classifier: License :: Repoze Public License
